kinematics/__init__.py
kinematics/attitude.py
kinematics/sphere.py
kinematics/tests/__init__.py
kinematics/tests/test_attitude.py
kinematics/tests/test_sphere.py
kinematics-0.1.7.dist-info/LICENSE
kinematics-0.1.7.dist-info/METADATA
kinematics-0.1.7.dist-info/WHEEL
kinematics-0.1.7.dist-info/top_level.txt
kinematics-0.1.7.dist-info/RECORD
