Metadata-Version: 2.1
Name: kinematics
Version: 0.1.7
Summary: A kinematics library
Home-page: https://github.com/skulumani/kinematics
Author: Shankar Kulumani
Author-email: shanks.k@gmail.com
License: GPLv3
Keywords: geometry attitude kinematics
Platform: UNKNOWN
Classifier: Development Status :: 3 - Alpha
Classifier: Intended Audience :: Science/Research
Classifier: Topic :: Software Development :: Libraries :: Python Modules
Classifier: License :: OSI Approved :: GNU General Public License v3 (GPLv3)
Classifier: Programming Language :: Python :: 3.4
Classifier: Programming Language :: Python :: 3.5
Classifier: Programming Language :: Python :: 3.6
Classifier: Programming Language :: Python :: 3.7
Requires-Python: >=3.4
Provides-Extra: test
